django_evolution/__init__.py
django_evolution/admin.py
django_evolution/conf.py
django_evolution/consts.py
django_evolution/deprecation.py
django_evolution/diff.py
django_evolution/errors.py
django_evolution/mock_models.py
django_evolution/models.py
django_evolution/placeholders.py
django_evolution/serialization.py
django_evolution/signals.py
django_evolution/signature.py
django_evolution/support.py
django_evolution/builtin_evolutions/__init__.py
django_evolution/builtin_evolutions/admin_move_to_migrations.py
django_evolution/builtin_evolutions/auth_delete_message.py
django_evolution/builtin_evolutions/auth_move_to_migrations.py
django_evolution/builtin_evolutions/auth_unique_together_baseline.py
django_evolution/builtin_evolutions/contenttypes_move_to_migrations.py
django_evolution/builtin_evolutions/contenttypes_unique_together_baseline.py
django_evolution/builtin_evolutions/flatpages_move_to_migrations.py
django_evolution/builtin_evolutions/redirects_move_to_migrations.py
django_evolution/builtin_evolutions/session_expire_date_db_index.py
django_evolution/builtin_evolutions/sessions_move_to_migrations.py
django_evolution/builtin_evolutions/sites_move_to_migrations.py
django_evolution/compat/__init__.py
django_evolution/compat/apps.py
django_evolution/compat/commands.py
django_evolution/compat/datastructures.py
django_evolution/compat/db.py
django_evolution/compat/models.py
django_evolution/compat/picklers.py
django_evolution/compat/py23.py
django_evolution/compat/six.py
django_evolution/compat/translation.py
django_evolution/compat/patches/__init__.py
django_evolution/compat/patches/django1_8__1_10_mysql_preserve_db_index.py
django_evolution/compat/patches/django2_0_quote_unique_index_name.py
django_evolution/compat/patches/mysqlclient_django_pre_2_encoder_bytes.py
django_evolution/compat/patches/python3_10_collection_imports.py
django_evolution/compat/patches/sqlite_legacy_alter_table.py
django_evolution/db/__init__.py
django_evolution/db/common.py
django_evolution-2.4.2.dist-info/AUTHORS
django_evolution-2.4.2.dist-info/LICENSE
django_evolution-2.4.2.dist-info/METADATA
django_evolution-2.4.2.dist-info/WHEEL
django_evolution-2.4.2.dist-info/top_level.txt
django_evolution-2.4.2.dist-info/RECORD
